hacked_http/_httplib.py
hacked_http/_urllib2.py
hacked_http/__init__.py
hacked_http-0.0.1.dist-info/DESCRIPTION.rst
hacked_http-0.0.1.dist-info/RECORD
hacked_http-0.0.1.dist-info/metadata.json
hacked_http-0.0.1.dist-info/METADATA
hacked_http-0.0.1.dist-info/top_level.txt
hacked_http-0.0.1.dist-info/WHEEL
