Metadata-Version: 2.0
Name: hacked-http
Version: 0.0.1
Summary: Hacked Urllib2 는 warning.or.kr 같은 방어벽을 뚫는데 목적이 있습니다.
Home-page: https://bitbucket.org/jochangmin/hacked-urllib2
Author: Chang Min Jo (Anderson)
Author-email: a141890@{nospam}gmail.com
License: MIT
Download-URL: https://bitbucket.org/jochangmin/hacked-urllib2/get/125df231b1ef.zip
Platform: any
Classifier: Intended Audience :: Developers
Classifier: License :: OSI Approved :: MIT License
Classifier: Operating System :: OS Independent
Classifier: Programming Language :: Python
Classifier: Programming Language :: Python :: 2
Classifier: Programming Language :: Python :: 2.6
Classifier: Programming Language :: Python :: 2.7
Classifier: Programming Language :: Python :: 3
Classifier: Programming Language :: Python :: 3.1
Classifier: Programming Language :: Python :: 3.2
Classifier: Programming Language :: Python :: Implementation :: CPython
Classifier: Topic :: Database
Classifier: Topic :: Software Development :: Libraries :: Python Modules
